{"reqs":"This section is restricted to students in the Bachelor and Master of Management Dual Degree program.\nThis section is restricted to students in the Bachelor and Master of Management Dual Degree program.\nThis section is restricted to students in the Bachelor and Master of Management Dual Degree program.\nThis section is restricted to students in the Bachelor and Master of Management Dual Degree program.\nThis section is restricted to students in the Bachelor and Master of Management Dual Degree program.\n","courseName":"Business Immersion","courseNumber":"120","credits":"Credits: 3","description":"A broad introduction to the field of business and how the different disciplines within business interact and combine in business decision-making. For Master of Management - Dual Degree Option students only.","sections":[{"section":"DD1"},{"section":"DD3"},{"section":"DD2"},{"section":"DD5"},{"section":"DD4"}]}