{"reqs":"Pre-reqs: EOSC 329. (or permission of the instructor.)\n7-day Field School held one week after exams. First day after exams, class in EOSM 135 until noon.\n","courseName":"Field Techniques in Groundwater Hydrology","courseNumber":"428","credits":"Credits: 3","description":"Hydraulic head measurements, water-quality sampling, pump and slug testing, infiltration measurements, profiling techniques. Held over five days after spring term at the Richmond groundwater hydrology field-school site. Enrolment limitations.","sections":[{"section":"201"}]}