{"reqs":"Pre-reqs: All of MATH 101, MATH 152, PHYS 170 and one of APSC 150, APSC 151 and either (a) PHYS 153 or (b) all of PHYS 157, PHYS 158, PHYS 159.\nCo-reqs: All of ENGL 112, MECH 221.\n","courseName":"Technical Skills Practicum","courseNumber":"220","credits":"Credits: 4","description":"Engineering graphics, spatial visualization, CAD, equation solvers, machine shop practice, electronic circuit construction and troubleshooting, elements of engineering science.","sections":[{"section":"101"}]}