{"reqs":"With 403G. An analysis-and-practice class, students will invent short compositions incorporating rhythm techniques found in a variety of world traditions, and teach them to one another orally.\n","courseName":"Topics in Ethnomusicology - ORAL COMPOSITION","courseNumber":"530C","credits":"Credits: 3","description":"Topics involving methodology and fieldwork in non-Western traditions. Topics will vary and students should consult the School as to areas of focus in any given term.","sections":[{"section":"001"}]}