{"reqs":"This course is for BMUS students and for students in Arts or other faculties who intend to major or minor in Music. Registration will be confirmed only for students who pass a placement test on the first Wednesday of classes. BMus students: select MUSC 100 lecture + tutorial. Other students: e-mail Dr. John Roeder at j.roeder@ubc.ca.\n","courseName":"Principles of Musical Form","courseNumber":"100","credits":"Credits: 3","description":"Fundamental materials and processes of music - rhythmic, melodic, textural and harmonic - and how they create small-scale structures in a variety of styles. Compositional and analytical applications.","sections":[{"section":"001"},{"section":"T01"},{"section":"T03"},{"section":"T02"}]}