{"reqs":"Pre-reqs: ARBC 101.\nStudents who have received credit for ARBC 300 can not also receive credit for ARBC 101 or 102\nIf the course is full or blocked please register in the wait list.\nStudents who have received credit for ARBC 300 can not also receive credit for ARBC 101 or 102.\nStudents will be moved from the Wait List into the main course on a first come first served basis as spots open up.\n","courseName":"Introduction to the Grammar and Vocabulary of Classic Arabic II","courseNumber":"102","credits":"Credits: 3","description":"","sections":[{"section":"001"},{"section":"002"}]}