{"reqs":"First class is September 8th, 2015. Room: BC Cancer Agency (Gordon and Leslie Diamond Family Theatre).\nFirst Class is September 8th, 2015. Room: BC Cancer Agency (Gordon and Leslie Diamond Family Theatre)\nFirst class is January 4, 2016. Room: BC Cancer Agency (Gordon and Leslie Diamond Family Theatre).\n","courseName":"Seminar","courseNumber":"535","credits":"Credits: 2","description":"Attendance required of all M.Sc. candidates in the Department.","sections":[{"section":"002"},{"section":"003"}]}