{"reqs":"ADVANCED CONCEPTS IN CARDIOVASCULAR PHYSIOLOGY AND REHABILITATION. The purpose of the course is to examine advanced concepts in cardiovascular physiology and rehabilitation. This course involves a strong practical component incorporating self-directed learning strategies throughout. Students are expected to develop and participate in research based on actual practice. Students may work with diverse clientele including children, the elderly, patients with cardiovascular disease, transplant patients, and/or persons with spinal cord injury. Instruction will take place within a traditional laboratory, a field-based setting, and/or clinical settings.\n","courseName":"Special Topics in Kinesiology - SPEC TPCS KIN","courseNumber":"500C","credits":"Credits: 3","description":"","sections":[{"section":"001"}]}