{"reqs":"When wait-lists are used, it is STUDENTS' RESPONSIBILITY to check the Web for changes made to their registration\nStudents must register for the lab section first and then the lecture, both must be in the same term\nWhen wait-lists are used, it is STUDENTS' RESPONSIBILITY to check the Web for changes made to their registration\nStudents must register for the lab section first and then the lecture, both must be in the same term\nStudents must register for the lab section first and then the lecture, both must be in the same term\nStudents must register for the lab section first and then the lecture, both must be in the same term\nStudents must register for the lab section first and then the lecture, both must be in the same term\nStudents must register for the lab section first and then the lecture, both must be in the same term\n","courseName":"Anatomy and Physiology II","courseNumber":"191","credits":"Credits: 3","description":"Structure and function of the digestive, endocrine, urinary, circulatory and respiratory systems. Special emphasis on effects of exercise. Please consult the School of Kinesiology Credit Exclusion Lists: http://www.calendar.ubc.ca/vancouver/index.cfm?tree=12,205,253,1477.","sections":[{"section":"L1F"},{"section":"001"},{"section":"L1E"},{"section":"901"},{"section":"L1B"},{"section":"L1A"},{"section":"L1D"},{"section":"L1C"}]}