{"reqs":"Pre-reqs: APSC 172.\nThis section is reserved for UBC Vantage College students only.\nThis section is reserved for UBC Vantage College students only.\n","courseName":"Engineering Analysis II","courseNumber":"173","credits":"Credits: 3","description":"Integrals and transcendental functions, techniques of integration, applications of integration, polar coordinates, infinite sequences and series, vectors and the geometry of space, and partial derivatives.","sections":[{"section":"VT2"},{"section":"VT1"},{"section":"VE1"}]}